Workbook

Sheet TITULAR
A2: IR FÁCIL | C2: 1. DADOS DO TITULAR
A3: Imposto de Renda | C3: preencha os dados da sua pessoa física abaixo
C4: Preencha as células sombreadas. Os dados de exemplo são fictícios: substitua pelos seus.
C5: ANO-CALENDÁRIO | D5: 2025
A6: =HYPERLINK("#'TITULAR'!A1","TITULAR") -> TITULAR | C6: NOME | D6: Joana Exemplo da Silva
C7: CPF | D7: 123.456.789-09
A8: =HYPERLINK("#'INFORMES'!A1","INFORMES") -> INFORMES | C8: NASCIMENTO | D8: 33008
C9: TÍTULO DE ELEITOR | D9: 012345678901
A10: =HYPERLINK("#'NOTAS'!A1","NOTAS") -> NOTAS | C10: CÔNJUGE | D10: Carlos Exemplo da Silva
C11: RUA | D11: Rua dos Limoeiros, Residencial das Flores - Nº 180
C12: RUA ABREVIADA (automático) | D12: =IF(D11="","",IF(LEN(D11)>30,LEFT(D11,29)&"…",D11)) -> Rua dos Limoeiros, Residencia…
C13: CEP | D13: 01000-000
A14: ="Ano-calendário "&Ano_Calendario -> Ano-calendário 2025 | C14: TELEFONE | D14: (11) 3000-0000
C15: CELULAR | D15: (11) 90000-0000
C16: E-MAIL | D16: joana.exemplo@email.com
C17: HOUVE ALTERAÇÕES DA ENTREGA ANTERIOR | D17: SIM
C18: DEPENDENTE CÔNJUGE | D18: NÃO | E18: =IF(AND(D18="SIM",D10=""),"Atenção: informe o nome do cônjuge","")
C19: RESIDENTE DO EXTERIOR | D19: NÃO
C21: PREENCHIMENTO | D21: =(COUNTA(D5:D11)+COUNTA(D13:D19))/(ROWS(D5:D11)+ROWS(D13:D19)) -> 1 | E21: dos campos desta tela preenchidos
D23: =HYPERLINK("#'INFORMES'!A1","PRÓXIMO →") -> PRÓXIMO →

Sheet INFORMES
A2: IR FÁCIL | C2: 2. INFORMES DE RENDIMENTOS
A3: Imposto de Renda | C3: informe cada fonte pagadora que enviou um informe de rendimentos no ano-calendário
C4: Preencha as células sombreadas. Os dados de exemplo são fictícios: substitua pelos seus.
A6: =HYPERLINK("#'TITULAR'!A1","TITULAR") -> TITULAR | C6: FONTE PAGADORA | D6: CNPJ / CPF | E6: TIPO DE RENDIMENTO | F6: RENDIMENTO ANUAL (R$) | G6: IR RETIDO (R$) | H6: COMPROVANTE
C7: Empresa Exemplo Ltda | D7: 12.345.678/0001-90 | E7: Salário | F7: 84000 | G7: 6120.5 | H7: Recebido
A8: =HYPERLINK("#'INFORMES'!A1","INFORMES") -> INFORMES | C8: Banco Exemplo S.A. | D8: 98.765.432/0001-10 | E8: Aplicações financeiras | F8: 3200 | G8: 480 | H8: Pendente
C9: Imobiliária Modelo Ltda | D9: 11.222.333/0001-44 | E9: Aluguel | F9: 18000 | G9: 0 | H9: Recebido
A10: =HYPERLINK("#'NOTAS'!A1","NOTAS") -> NOTAS
A14: ="Ano-calendário "&Ano_Calendario -> Ano-calendário 2025
C22: TOTAL | F22: =SUM(F7:F21) -> 105200 | G22: =SUM(G7:G21) -> 6600.5
C24: RESUMO POR TIPO DE RENDIMENTO
C25: TIPO | D25: RENDIMENTO (R$) | E25: IR RETIDO (R$)
C26: =Listas!$B$2 -> Salário | D26: =SUMIF($E$7:$E$21,$C26,$F$7:$F$21) -> 84000 | E26: =SUMIF($E$7:$E$21,$C26,$G$7:$G$21) -> 6120.5
C27: =Listas!$B$3 -> Aluguel | D27: =SUMIF($E$7:$E$21,$C27,$F$7:$F$21) -> 18000 | E27: =SUMIF($E$7:$E$21,$C27,$G$7:$G$21) -> 0
C28: =Listas!$B$4 -> Pró-labore | D28: =SUMIF($E$7:$E$21,$C28,$F$7:$F$21) -> 0 | E28: =SUMIF($E$7:$E$21,$C28,$G$7:$G$21) -> 0
C29: =Listas!$B$5 -> Aplicações financeiras | D29: =SUMIF($E$7:$E$21,$C29,$F$7:$F$21) -> 3200 | E29: =SUMIF($E$7:$E$21,$C29,$G$7:$G$21) -> 480
C30: =Listas!$B$6 -> Dividendos | D30: =SUMIF($E$7:$E$21,$C30,$F$7:$F$21) -> 0 | E30: =SUMIF($E$7:$E$21,$C30,$G$7:$G$21) -> 0
C31: =Listas!$B$7 -> Outros | D31: =SUMIF($E$7:$E$21,$C31,$F$7:$F$21) -> 0 | E31: =SUMIF($E$7:$E$21,$C31,$G$7:$G$21) -> 0
C32: TOTAL | D32: =SUM(D26:D31) -> 105200 | E32: =SUM(E26:E31) -> 6600.5 | F32: =IF(D32=F22,"","Atenção: há rendimento sem tipo informado")
C34: =HYPERLINK("#'TITULAR'!A1","← VOLTAR") -> ← VOLTAR | E34: =HYPERLINK("#'NOTAS'!A1","PRÓXIMO →") -> PRÓXIMO →

Sheet NOTAS
A2: IR FÁCIL | C2: 3. NOTAS E DESPESAS DEDUTÍVEIS
A3: Imposto de Renda | C3: registre despesas médicas, de educação e outras que podem ser deduzidas
C4: Preencha as células sombreadas. Os dados de exemplo são fictícios: substitua pelos seus.
A6: =HYPERLINK("#'TITULAR'!A1","TITULAR") -> TITULAR | C6: DATA | D6: DESCRIÇÃO | E6: CATEGORIA | F6: VALOR (R$) | G6: Nº DO RECIBO / NOTA | H6: COMPROVANTE
C7: 45728 | D7: Consulta clínica geral | E7: Saúde | F7: 350 | G7: Recibo 0012 | H7: Recebido
A8: =HYPERLINK("#'INFORMES'!A1","INFORMES") -> INFORMES | C8: 45693 | D8: Mensalidade escolar (fevereiro) | E8: Educação | F8: 1200 | G8: NF 4587 | H8: Recebido
C9: 45858 | D9: Contribuição PGBL | E9: Previdência privada (PGBL) | F9: 2400 | G9: Informe 2025 | H9: Pendente
A10: =HYPERLINK("#'NOTAS'!A1","NOTAS") -> NOTAS
A14: ="Ano-calendário "&Ano_Calendario -> Ano-calendário 2025
D27: TOTAL | F27: =SUM(F7:F26) -> 3950
D28: RESUMO POR CATEGORIA
D29: CATEGORIA | E29: LANÇAMENTOS | F29: TOTAL (R$) | G29: % DO TOTAL
D30: =Listas!$C$2 -> Saúde | E30: =COUNTIF($E$7:$E$26,$D30) -> 1 | F30: =SUMIF($E$7:$E$26,$D30,$F$7:$F$26) -> 350 | G30: =IF($F$35=0,0,F30/$F$35) -> 0.088607595
D31: =Listas!$C$3 -> Educação | E31: =COUNTIF($E$7:$E$26,$D31) -> 1 | F31: =SUMIF($E$7:$E$26,$D31,$F$7:$F$26) -> 1200 | G31: =IF($F$35=0,0,F31/$F$35) -> 0.30379747
D32: =Listas!$C$4 -> Previdência privada (PGBL) | E32: =COUNTIF($E$7:$E$26,$D32) -> 1 | F32: =SUMIF($E$7:$E$26,$D32,$F$7:$F$26) -> 2400 | G32: =IF($F$35=0,0,F32/$F$35) -> 0.60759494
D33: =Listas!$C$5 -> Pensão alimentícia | E33: =COUNTIF($E$7:$E$26,$D33) -> 0 | F33: =SUMIF($E$7:$E$26,$D33,$F$7:$F$26) -> 0 | G33: =IF($F$35=0,0,F33/$F$35) -> 0
D34: =Listas!$C$6 -> Outras | E34: =COUNTIF($E$7:$E$26,$D34) -> 0 | F34: =SUMIF($E$7:$E$26,$D34,$F$7:$F$26) -> 0 | G34: =IF($F$35=0,0,F34/$F$35) -> 0
D35: TOTAL | E35: =SUM(E30:E34) -> 3 | F35: =SUM(F30:F34) -> 3950 | G35: =SUM(G30:G34) -> 1 | H35: =IF(ROUND(F35-F27,2)=0,"","Atenção: há despesa sem categoria")
D37: Limite anual de educação (por pessoa) | F37: 3561.5
D38: Educação considerada (até o limite) | F38: =MIN(F31,Limite_Educacao) -> 1200
D39: O limite é um valor de referência editável (premissa minha): confirme o vigente no site da Receita Federal.
C41: =HYPERLINK("#'INFORMES'!A1","← VOLTAR") -> ← VOLTAR | D41: =HYPERLINK("#'TITULAR'!A1","VOLTAR AO INÍCIO") -> VOLTAR AO INÍCIO

Sheet Listas
A1: SIM / NÃO | B1: TIPO DE RENDIMENTO | C1: CATEGORIA DE DESPESA | D1: COMPROVANTE
A2: SIM | B2: Salário | C2: Saúde | D2: Recebido
A3: NÃO | B3: Aluguel | C3: Educação | D3: Pendente
B4: Pró-labore | C4: Previdência privada (PGBL)
B5: Aplicações financeiras | C5: Pensão alimentícia
B6: Dividendos | C6: Outras
B7: Outros
